{
  "annotations": {
    "list": [
      {
        "builtIn": 1,
        "datasource": "-- Grafana --",
        "enable": true,
        "hide": true,
        "iconColor": "rgba(0, 211, 255, 1)",
        "name": "Annotations & Alerts",
        "type": "dashboard"
      }
    ]
  },
  "description": "",
  "editable": true,
  "gnetId": 928,
  "graphTooltip": 1,
  "id": 5,
  "iteration": 1555349223530,
  "links": [],
  "panels": [
    {
      "collapsed": false,
      "gridPos": {
        "h": 1,
        "w": 24,
        "x": 0,
        "y": 0
      },
      "id": 62044,
      "panels": [],
      "repeat": null,
      "title": "Quick overview",
      "type": "row"
    },
    {
      "cacheTimeout": null,
      "colorBackground": false,
      "colorValue": false,
      "colors": [
        "rgba(245, 54, 54, 0.9)",
        "rgba(237, 129, 40, 0.89)",
        "rgba(50, 172, 45, 0.97)"
      ],
      "datasource": "InfluxDB",
      "decimals": 1,
      "editable": true,
      "error": false,
      "format": "s",
      "gauge": {
        "maxValue": 100,
        "minValue": 0,
        "show": false,
        "thresholdLabels": false,
        "thresholdMarkers": true
      },
      "gridPos": {
        "h": 4,
        "w": 4,
        "x": 0,
        "y": 1
      },
      "height": "150",
      "id": 61858,
      "interval": null,
      "links": [],
      "mappingType": 1,
      "mappingTypes": [
        {
          "name": "value to text",
          "value": 1
        },
        {
          "name": "range to text",
          "value": 2
        }
      ],
      "maxDataPoints": 100,
      "nullPointMode": "connected",
      "nullText": null,
      "postfix": "",
      "postfixFontSize": "50%",
      "prefix": "",
      "prefixFontSize": "50%",
      "rangeMaps": [
        {
          "from": "null",
          "text": "N/A",
          "to": "null"
        }
      ],
      "sparkline": {
        "fillColor": "rgba(31, 118, 189, 0.18)",
        "full": false,
        "lineColor": "rgb(31, 120, 193)",
        "show": false
      },
      "tableColumn": "",
      "targets": [
        {
          "dsType": "influxdb",
          "groupBy": [
            {
              "params": [
                "$interval"
              ],
              "type": "time"
            },
            {
              "params": [
                "null"
              ],
              "type": "fill"
            }
          ],
          "measurement": "system",
          "policy": "default",
          "refId": "A",
          "resultFormat": "time_series",
          "select": [
            [
              {
                "params": [
                  "uptime"
                ],
                "type": "field"
              },
              {
                "params": [],
                "type": "last"
              }
            ]
          ],
          "tags": [
            {
              "key": "host",
              "operator": "=~",
              "value": "/^$server$/"
            }
          ]
        }
      ],
      "thresholds": "",
      "title": "Uptime",
      "type": "singlestat",
      "valueFontSize": "100%",
      "valueMaps": [
        {
          "op": "=",
          "text": "N/A",
          "value": "null"
        }
      ],
      "valueName": "current"
    },
    {
      "cacheTimeout": null,
      "colorBackground": false,
      "colorValue": true,
      "colors": [
        "rgba(50, 172, 45, 0.97)",
        "rgba(237, 129, 40, 0.89)",
        "rgba(245, 54, 54, 0.9)"
      ],
      "datasource": "InfluxDB",
      "editable": true,
      "error": false,
      "format": "percent",
      "gauge": {
        "maxValue": 100,
        "minValue": 0,
        "show": true,
        "thresholdLabels": false,
        "thresholdMarkers": true
      },
      "gridPos": {
        "h": 4,
        "w": 6,
        "x": 4,
        "y": 1
      },
      "height": "150",
      "id": 61861,
      "interval": null,
      "links": [
        {
          "dashboard": "CPU Statistics",
          "title": "CPU Statistics",
          "type": "dashboard",
          "url": "/d/Q5gqOaRWk/cpu-statistics"
        }
      ],
      "mappingType": 1,
      "mappingTypes": [
        {
          "name": "value to text",
          "value": 1
        },
        {
          "name": "range to text",
          "value": 2
        }
      ],
      "maxDataPoints": 100,
      "nullPointMode": "connected",
      "nullText": null,
      "postfix": "",
      "postfixFontSize": "50%",
      "prefix": "",
      "prefixFontSize": "50%",
      "rangeMaps": [
        {
          "from": "null",
          "text": "N/A",
          "to": "null"
        }
      ],
      "sparkline": {
        "fillColor": "rgba(31, 118, 189, 0.18)",
        "full": false,
        "lineColor": "rgb(31, 120, 193)",
        "show": false
      },
      "tableColumn": "",
      "targets": [
        {
          "dsType": "influxdb",
          "groupBy": [
            {
              "params": [
                "$interval"
              ],
              "type": "time"
            },
            {
              "params": [
                "null"
              ],
              "type": "fill"
            }
          ],
          "measurement": "cpu",
          "orderByTime": "ASC",
          "policy": "default",
          "refId": "A",
          "resultFormat": "time_series",
          "select": [
            [
              {
                "params": [
                  "usage_idle"
                ],
                "type": "field"
              },
              {
                "params": [],
                "type": "last"
              },
              {
                "params": [
                  "* -1 + 100"
                ],
                "type": "math"
              }
            ]
          ],
          "tags": [
            {
              "key": "host",
              "operator": "=~",
              "value": "/^$server$/"
            },
            {
              "condition": "AND",
              "key": "cpu",
              "operator": "=",
              "value": "cpu-total"
            }
          ]
        }
      ],
      "thresholds": "70,80,90",
      "title": "CPU usage",
      "type": "singlestat",
      "valueFontSize": "80%",
      "valueMaps": [
        {
          "op": "=",
          "text": "N/A",
          "value": "null"
        }
      ],
      "valueName": "current"
    },
    {
      "cacheTimeout": null,
      "colorBackground": false,
      "colorValue": true,
      "colors": [
        "rgba(50, 172, 45, 0.97)",
        "rgba(237, 129, 40, 0.89)",
        "rgba(245, 54, 54, 0.9)"
      ],
      "datasource": "InfluxDB",
      "editable": true,
      "error": false,
      "format": "percent",
      "gauge": {
        "maxValue": 100,
        "minValue": 0,
        "show": true,
        "thresholdLabels": false,
        "thresholdMarkers": true
      },
      "gridPos": {
        "h": 4,
        "w": 7,
        "x": 10,
        "y": 1
      },
      "height": "150",
      "id": 61860,
      "interval": null,
      "links": [
        {
          "dashboard": "RAM Statistics",
          "title": "RAM Statistics",
          "type": "dashboard",
          "url": "/d/QrNGFaRZz/ram-statistics"
        }
      ],
      "mappingType": 1,
      "mappingTypes": [
        {
          "name": "value to text",
          "value": 1
        },
        {
          "name": "range to text",
          "value": 2
        }
      ],
      "maxDataPoints": 100,
      "nullPointMode": "connected",
      "nullText": null,
      "postfix": "",
      "postfixFontSize": "50%",
      "prefix": "",
      "prefixFontSize": "50%",
      "rangeMaps": [
        {
          "from": "null",
          "text": "N/A",
          "to": "null"
        }
      ],
      "sparkline": {
        "fillColor": "rgba(31, 118, 189, 0.18)",
        "full": false,
        "lineColor": "rgb(31, 120, 193)",
        "show": false
      },
      "tableColumn": "",
      "targets": [
        {
          "dsType": "influxdb",
          "groupBy": [
            {
              "params": [
                "$interval"
              ],
              "type": "time"
            },
            {
              "params": [
                "null"
              ],
              "type": "fill"
            }
          ],
          "measurement": "mem",
          "orderByTime": "ASC",
          "policy": "default",
          "refId": "A",
          "resultFormat": "time_series",
          "select": [
            [
              {
                "params": [
                  "used_percent"
                ],
                "type": "field"
              },
              {
                "params": [],
                "type": "last"
              }
            ]
          ],
          "tags": [
            {
              "key": "host",
              "operator": "=~",
              "value": "/^$server$/"
            }
          ]
        }
      ],
      "thresholds": "70,80,90",
      "title": "RAM usage",
      "type": "singlestat",
      "valueFontSize": "80%",
      "valueMaps": [
        {
          "op": "=",
          "text": "N/A",
          "value": "null"
        }
      ],
      "valueName": "current"
    },
    {
      "cacheTimeout": null,
      "colorBackground": false,
      "colorValue": true,
      "colors": [
        "rgba(50, 172, 45, 0.97)",
        "rgba(237, 129, 40, 0.89)",
        "rgba(245, 54, 54, 0.9)"
      ],
      "datasource": "InfluxDB",
      "decimals": 0,
      "editable": true,
      "error": false,
      "format": "percent",
      "gauge": {
        "maxValue": 100,
        "minValue": 0,
        "show": true,
        "thresholdLabels": false,
        "thresholdMarkers": true
      },
      "gridPos": {
        "h": 4,
        "w": 7,
        "x": 17,
        "y": 1
      },
      "height": "150",
      "id": 61863,
      "interval": null,
      "links": [
        {
          "dashboard": "Disk Usage and I/O",
          "title": "Disk Usage and I/O",
          "type": "dashboard",
          "url": "/d/gjFKK-RZk/disk-usage-and-i-o"
        }
      ],
      "mappingType": 1,
      "mappingTypes": [
        {
          "name": "value to text",
          "value": 1
        },
        {
          "name": "range to text",
          "value": 2
        }
      ],
      "maxDataPoints": 100,
      "nullPointMode": "connected",
      "nullText": null,
      "postfix": "",
      "postfixFontSize": "50%",
      "prefix": "",
      "prefixFontSize": "50%",
      "rangeMaps": [
        {
          "from": "null",
          "text": "N/A",
          "to": "null"
        }
      ],
      "sparkline": {
        "fillColor": "rgba(31, 118, 189, 0.18)",
        "full": false,
        "lineColor": "rgb(31, 120, 193)",
        "show": false
      },
      "tableColumn": "",
      "targets": [
        {
          "dsType": "influxdb",
          "groupBy": [
            {
              "params": [
                "$interval"
              ],
              "type": "time"
            },
            {
              "params": [
                "null"
              ],
              "type": "fill"
            }
          ],
          "measurement": "disk",
          "orderByTime": "ASC",
          "policy": "default",
          "refId": "A",
          "resultFormat": "time_series",
          "select": [
            [
              {
                "params": [
                  "used_percent"
                ],
                "type": "field"
              },
              {
                "params": [],
                "type": "last"
              }
            ]
          ],
          "tags": [
            {
              "key": "host",
              "operator": "=~",
              "value": "/^$server$/"
            }
          ]
        }
      ],
      "thresholds": "50,70,90",
      "title": "Disk Usage",
      "type": "singlestat",
      "valueFontSize": "80%",
      "valueMaps": [
        {
          "op": "=",
          "text": "N/A",
          "value": "null"
        }
      ],
      "valueName": "current"
    },
    {
      "cacheTimeout": null,
      "colorBackground": false,
      "colorValue": false,
      "colors": [
        "rgba(245, 54, 54, 0.9)",
        "rgba(237, 129, 40, 0.89)",
        "rgba(50, 172, 45, 0.97)"
      ],
      "datasource": "InfluxDB",
      "decimals": 2,
      "editable": true,
      "error": false,
      "format": "Bps",
      "gauge": {
        "maxValue": 100,
        "minValue": 0,
        "show": false,
        "thresholdLabels": false,
        "thresholdMarkers": true
      },
      "gridPos": {
        "h": 7,
        "w": 24,
        "x": 0,
        "y": 5
      },
      "height": "150",
      "id": 61867,
      "interval": null,
      "links": [
        {
          "dashboard": "Network Overview",
          "title": "Network Overview",
          "type": "dashboard",
          "url": "/d/Vy4qpaRZz/network-overview"
        }
      ],
      "mappingType": 1,
      "mappingTypes": [
        {
          "name": "value to text",
          "value": 1
        },
        {
          "name": "range to text",
          "value": 2
        }
      ],
      "maxDataPoints": 100,
      "nullPointMode": "connected",
      "nullText": null,
      "postfix": "",
      "postfixFontSize": "50%",
      "prefix": "",
      "prefixFontSize": "50%",
      "rangeMaps": [
        {
          "from": "null",
          "text": "N/A",
          "to": "null"
        }
      ],
      "sparkline": {
        "fillColor": "rgba(31, 118, 189, 0.18)",
        "full": false,
        "lineColor": "rgb(31, 120, 193)",
        "show": true
      },
      "tableColumn": "",
      "targets": [
        {
          "groupBy": [
            {
              "params": [
                "$__interval"
              ],
              "type": "time"
            },
            {
              "params": [
                "null"
              ],
              "type": "fill"
            }
          ],
          "measurement": "net",
          "orderByTime": "ASC",
          "policy": "default",
          "refId": "A",
          "resultFormat": "time_series",
          "select": [
            [
              {
                "params": [
                  "bytes_recv"
                ],
                "type": "field"
              },
              {
                "params": [],
                "type": "mean"
              },
              {
                "params": [
                  "10s"
                ],
                "type": "non_negative_derivative"
              },
              {
                "params": [
                  "*8"
                ],
                "type": "math"
              }
            ]
          ],
          "tags": [
            {
              "key": "host",
              "operator": "=~",
              "value": "/^$server$/"
            },
            {
              "condition": "AND",
              "key": "interface",
              "operator": "=~",
              "value": "/^$netif$/"
            }
          ]
        }
      ],
      "thresholds": "30,40,50",
      "title": "Network Usage",
      "type": "singlestat",
      "valueFontSize": "100%",
      "valueMaps": [
        {
          "op": "=",
          "text": "N/A",
          "value": "null"
        }
      ],
      "valueName": "current"
    }
  ],
  "refresh": "5s",
  "schemaVersion": 18,
  "style": "dark",
  "tags": [
    "influxdb",
    "telegraf"
  ],
  "templating": {
    "list": [
      {
        "allFormat": "glob",
        "current": {
          "text": "InfluxDB",
          "value": "InfluxDB"
        },
        "datasource": "InfluxDB telegraf",
        "hide": 0,
        "includeAll": false,
        "label": "",
        "multi": false,
        "name": "datasource",
        "options": [],
        "query": "influxdb",
        "refresh": 1,
        "regex": "",
        "skipUrlSync": false,
        "type": "datasource"
      },
      {
        "auto": true,
        "auto_count": 100,
        "auto_min": "30s",
        "current": {
          "text": "10s",
          "value": "10s"
        },
        "datasource": null,
        "hide": 0,
        "includeAll": false,
        "label": "Sampling",
        "multi": false,
        "name": "inter",
        "options": [
          {
            "selected": false,
            "text": "auto",
            "value": "$__auto_interval_inter"
          },
          {
            "selected": true,
            "text": "10s",
            "value": "10s"
          },
          {
            "selected": false,
            "text": "30s",
            "value": "30s"
          },
          {
            "selected": false,
            "text": "1m",
            "value": "1m"
          },
          {
            "selected": false,
            "text": "2m",
            "value": "2m"
          },
          {
            "selected": false,
            "text": "5m",
            "value": "5m"
          },
          {
            "selected": false,
            "text": "10m",
            "value": "10m"
          },
          {
            "selected": false,
            "text": "30m",
            "value": "30m"
          },
          {
            "selected": false,
            "text": "1h",
            "value": "1h"
          }
        ],
        "query": "10s,30s,1m,2m,5m,10m,30m,1h",
        "refresh": 2,
        "skipUrlSync": false,
        "type": "interval"
      },
      {
        "allValue": null,
        "current": {
          "text": "9753f690e862",
          "value": "9753f690e862"
        },
        "datasource": "InfluxDB",
        "definition": "",
        "hide": 0,
        "includeAll": false,
        "label": "Host",
        "multi": false,
        "name": "server",
        "options": [],
        "query": "SHOW TAG VALUES FROM system WITH KEY=host",
        "refresh": 1,
        "regex": "",
        "skipUrlSync": false,
        "sort": 0,
        "tagValuesQuery": null,
        "tags": [],
        "tagsQuery": null,
        "type": "query",
        "useTags": false
      },
      {
        "allValue": null,
        "current": {
          "text": "All",
          "value": "$__all"
        },
        "datasource": "$datasource",
        "definition": "",
        "hide": 0,
        "includeAll": true,
        "label": "Mountpoint",
        "multi": true,
        "name": "mountpoint",
        "options": [],
        "query": "SHOW TAG VALUES FROM \"disk\" WITH KEY = \"path\" WHERE host =~ /$server/",
        "refresh": 1,
        "regex": "",
        "skipUrlSync": false,
        "sort": 0,
        "tagValuesQuery": null,
        "tags": [],
        "tagsQuery": null,
        "type": "query",
        "useTags": false
      },
      {
        "allValue": null,
        "current": {
          "text": "All",
          "value": "$__all"
        },
        "datasource": "$datasource",
        "definition": "",
        "hide": 0,
        "includeAll": true,
        "label": "CPU",
        "multi": true,
        "name": "cpu",
        "options": [],
        "query": "SHOW TAG VALUES FROM \"cpu\" WITH KEY = \"cpu\" WHERE host =~ /$server/",
        "refresh": 1,
        "regex": "/cpu[0-9]/",
        "skipUrlSync": false,
        "sort": 1,
        "tagValuesQuery": null,
        "tags": [],
        "tagsQuery": null,
        "type": "query",
        "useTags": false
      },
      {
        "allValue": null,
        "current": {
          "text": "All",
          "value": [
            "$__all"
          ]
        },
        "datasource": "$datasource",
        "definition": "",
        "hide": 0,
        "includeAll": true,
        "label": "Disk",
        "multi": true,
        "name": "disk",
        "options": [],
        "query": "SHOW TAG VALUES FROM \"diskio\" WITH KEY = \"name\" WHERE host =~ /$server/",
        "refresh": 1,
        "regex": "/[a-z]d[\\D]$/",
        "skipUrlSync": false,
        "sort": 0,
        "tagValuesQuery": null,
        "tags": [],
        "tagsQuery": null,
        "type": "query",
        "useTags": false
      },
      {
        "allValue": null,
        "current": {
          "text": "All",
          "value": "$__all"
        },
        "datasource": "$datasource",
        "definition": "",
        "hide": 0,
        "includeAll": true,
        "label": "Network interface",
        "multi": true,
        "name": "netif",
        "options": [],
        "query": "SHOW TAG VALUES FROM \"net\" WITH KEY = \"interface\" WHERE host =~ /$server/",
        "refresh": 1,
        "regex": "^(?!.*veth|all|tap).*$",
        "skipUrlSync": false,
        "sort": 1,
        "tagValuesQuery": null,
        "tags": [],
        "tagsQuery": null,
        "type": "query",
        "useTags": false
      }
    ]
  },
  "time": {
    "from": "now-1h",
    "to": "now"
  },
  "timepicker": {
    "refresh_intervals": [
      "5s",
      "10s",
      "30s",
      "1m",
      "5m",
      "15m",
      "30m",
      "1h",
      "2h",
      "1d"
    ],
    "time_options": [
      "5m",
      "15m",
      "1h",
      "6h",
      "12h",
      "24h",
      "2d",
      "7d",
      "30d"
    ]
  },
  "timezone": "browser",
  "title": "System Overview",
  "uid": "6mpoU4RWk",
  "version": 5
}